{
  "video_id": "24",
  "rally_id": "88",
  "source_video": "/home/dang.cpm/__MY_SPACE__/VinUni/Data-Mining/project/dataset/ShuttleSet_raw_videos/24 - Anthony_Sinisuka_Ginting_Rasmus_Gemke_YONEX_Thailand_Open_2021_QuarterFinals.mp4",
  "start_frame": 110130,
  "end_frame": 110280,
  "fps": 30.0,
  "width": 1280,
  "height": 720,
  "frame_count": 134850,
  "decoder": "opencv",
  "processed_frames": 151,
  "device": "cuda:1",
  "model_file": "/home/dang.cpm/__MY_SPACE__/VinUni/Data-Mining/external_repos/TrackNetV3/exp/model_best.pt",
  "raw_csv": "project/outputs/shuttle_train_1_34/24/88_ball_raw.csv",
  "denoised_csv": "project/outputs/shuttle_train_1_34/24/88_ball_denoised.csv",
  "raw_validation": {
    "rows": 151,
    "visible_rows": 120,
    "coverage": 0.7947019867549668,
    "out_of_range_visible_rows": 0,
    "first_frame": 0,
    "last_frame": 150
  },
  "denoised_validation": {
    "rows": 151,
    "visible_rows": 125,
    "coverage": 0.8278145695364238,
    "out_of_range_visible_rows": 0,
    "first_frame": 0,
    "last_frame": 150
  },
  "denoise_stats": {
    "removed_jump_count": 17,
    "out_of_range_count": 0,
    "interpolated_count": 22
  },
  "runtime_sec": 3.41776442527771
}