{
  "video_id": "27",
  "rally_id": "20",
  "source_video": "/home/dang.cpm/__MY_SPACE__/VinUni/Data-Mining/project/dataset/ShuttleSet_raw_videos/27 - Viktor_Axelsen_Anthony_Sinisuka_Ginting_YONEX_Thailand_Open_2021_SemiFinals.mp4",
  "start_frame": 25590,
  "end_frame": 25830,
  "fps": 30.0,
  "width": 1280,
  "height": 720,
  "frame_count": 140250,
  "decoder": "opencv",
  "processed_frames": 241,
  "device": "cuda:1",
  "model_file": "/home/dang.cpm/__MY_SPACE__/VinUni/Data-Mining/external_repos/TrackNetV3/exp/model_best.pt",
  "raw_csv": "project/outputs/shuttle_train_1_34/27/20_ball_raw.csv",
  "denoised_csv": "project/outputs/shuttle_train_1_34/27/20_ball_denoised.csv",
  "raw_validation": {
    "rows": 241,
    "visible_rows": 238,
    "coverage": 0.9875518672199171,
    "out_of_range_visible_rows": 0,
    "first_frame": 0,
    "last_frame": 240
  },
  "denoised_validation": {
    "rows": 241,
    "visible_rows": 241,
    "coverage": 1.0,
    "out_of_range_visible_rows": 0,
    "first_frame": 0,
    "last_frame": 240
  },
  "denoise_stats": {
    "removed_jump_count": 21,
    "out_of_range_count": 0,
    "interpolated_count": 24
  },
  "runtime_sec": 5.25282621383667
}