{
  "video_id": "3",
  "rally_id": "91",
  "source_video": "/home/dang.cpm/__MY_SPACE__/VinUni/Data-Mining/project/dataset/ShuttleSet_raw_videos/03 - Kento_MOMOTA_CHOU_Tien_Chen_KOREA_OPEN_2019_Final.mp4",
  "start_frame": 87150,
  "end_frame": 87325,
  "fps": 25.0,
  "width": 1280,
  "height": 720,
  "frame_count": 107901,
  "decoder": "ffmpeg",
  "processed_frames": 176,
  "device": "cuda:1",
  "model_file": "/home/dang.cpm/__MY_SPACE__/VinUni/Data-Mining/external_repos/TrackNetV3/exp/model_best.pt",
  "raw_csv": "project/outputs/shuttle_train_1_34/3/91_ball_raw.csv",
  "denoised_csv": "project/outputs/shuttle_train_1_34/3/91_ball_denoised.csv",
  "raw_validation": {
    "rows": 176,
    "visible_rows": 150,
    "coverage": 0.8522727272727273,
    "out_of_range_visible_rows": 0,
    "first_frame": 0,
    "last_frame": 175
  },
  "denoised_validation": {
    "rows": 176,
    "visible_rows": 155,
    "coverage": 0.8806818181818182,
    "out_of_range_visible_rows": 0,
    "first_frame": 0,
    "last_frame": 175
  },
  "denoise_stats": {
    "removed_jump_count": 7,
    "out_of_range_count": 0,
    "interpolated_count": 12
  },
  "runtime_sec": 8.254294395446777
}