{
  "video_id": "23",
  "rally_id": "35",
  "source_video": "/home/dang.cpm/__MY_SPACE__/VinUni/Data-Mining/project/dataset/ShuttleSet_raw_videos/23 - Ng_Ka_Long_Angus_Lee_Cheuk_Yiu_YONEX_Thailand_Open_2021_QuarterFinals.mp4",
  "start_frame": 44730,
  "end_frame": 45420,
  "fps": 30.0,
  "width": 1280,
  "height": 720,
  "frame_count": 97050,
  "decoder": "opencv",
  "processed_frames": 691,
  "device": "cuda:1",
  "model_file": "/home/dang.cpm/__MY_SPACE__/VinUni/Data-Mining/external_repos/TrackNetV3/exp/model_best.pt",
  "raw_csv": "project/outputs/shuttle_train_1_34/23/35_ball_raw.csv",
  "denoised_csv": "project/outputs/shuttle_train_1_34/23/35_ball_denoised.csv",
  "raw_validation": {
    "rows": 691,
    "visible_rows": 652,
    "coverage": 0.9435600578871202,
    "out_of_range_visible_rows": 0,
    "first_frame": 0,
    "last_frame": 690
  },
  "denoised_validation": {
    "rows": 691,
    "visible_rows": 656,
    "coverage": 0.9493487698986975,
    "out_of_range_visible_rows": 0,
    "first_frame": 0,
    "last_frame": 690
  },
  "denoise_stats": {
    "removed_jump_count": 113,
    "out_of_range_count": 0,
    "interpolated_count": 117
  },
  "runtime_sec": 14.683803081512451
}