{
  "video_id": "21",
  "rally_id": "59",
  "source_video": "/home/dang.cpm/__MY_SPACE__/VinUni/Data-Mining/project/dataset/ShuttleSet_raw_videos/21 - An_Se_Young_Ratchanok_Intanon_YONEX_Thailand_Open_2021_QuarterFinals.mp4",
  "start_frame": 65040,
  "end_frame": 65190,
  "fps": 30.0,
  "width": 1280,
  "height": 720,
  "frame_count": 100349,
  "decoder": "opencv",
  "processed_frames": 151,
  "device": "cuda:1",
  "model_file": "/home/dang.cpm/__MY_SPACE__/VinUni/Data-Mining/external_repos/TrackNetV3/exp/model_best.pt",
  "raw_csv": "project/outputs/shuttle_train_1_34/21/59_ball_raw.csv",
  "denoised_csv": "project/outputs/shuttle_train_1_34/21/59_ball_denoised.csv",
  "raw_validation": {
    "rows": 151,
    "visible_rows": 141,
    "coverage": 0.9337748344370861,
    "out_of_range_visible_rows": 0,
    "first_frame": 0,
    "last_frame": 150
  },
  "denoised_validation": {
    "rows": 151,
    "visible_rows": 138,
    "coverage": 0.9139072847682119,
    "out_of_range_visible_rows": 0,
    "first_frame": 0,
    "last_frame": 150
  },
  "denoise_stats": {
    "removed_jump_count": 36,
    "out_of_range_count": 0,
    "interpolated_count": 33
  },
  "runtime_sec": 3.576714038848877
}